lean_reinforcement-0.3.0.dist-info/WHEEL
lean_reinforcement-0.3.0.dist-info/top_level.txt
lean_reinforcement-0.3.0.dist-info/METADATA
lean_reinforcement-0.3.0.dist-info/RECORD
lean_reinforcement-0.3.0.dist-info/licenses/LICENSE
ReProver/common_cy.html
ReProver/LICENSE
ReProver/.git
ReProver/common_cy.cpython-311-x86_64-linux-gnu.so
ReProver/common_cy.pyi
ReProver/common_cy.pyx
ReProver/.gitignore
ReProver/README.md
ReProver/mypy.ini
ReProver/pyproject.toml
ReProver/common.py
ReProver/common_cy.c
ReProver/__init__.py
ReProver/generation/datamodule.py
ReProver/generation/main.py
ReProver/generation/model.py
ReProver/generation/preprocess.py
ReProver/generation/__init__.py
ReProver/generation/confs/cli_lean4_random.yaml
ReProver/generation/confs/cli_lean4_novel_premises.yaml
ReProver/scripts/minimal_example.sh
ReProver/scripts/download_data.py
ReProver/scripts/trace_repos.py
ReProver/scripts/stats.py
ReProver/scripts/convert_checkpoint.py
ReProver/scripts/data_stats.py
ReProver/.github/workflows/format_code.yaml
ReProver/images/ReProver.jpg
ReProver/prover/tactic_generator.py
ReProver/prover/search_tree.py
ReProver/prover/evaluate.py
ReProver/prover/proof_search.py
ReProver/prover/__init__.py
ReProver/retrieval/datamodule.py
ReProver/retrieval/evaluate.py
ReProver/retrieval/main.py
ReProver/retrieval/model.py
ReProver/retrieval/__init__.py
ReProver/retrieval/index.py
ReProver/retrieval/confs/cli_lean4_random.yaml
ReProver/retrieval/confs/cli_lean4_novel_premises.yaml
ReProver/retrieval/confs/cli_dummy.yaml
ReProver/retrieval/bm25/README.md
ReProver/retrieval/bm25/main.py
ReProver/retrieval/bm25/train_tokenizer.py
ReProver/retrieval/bm25/__init__.py
lean_reinforcement/__init__.py
lean_reinforcement/agent/value_head.py
lean_reinforcement/agent/proxies.py
lean_reinforcement/agent/transformer.py
lean_reinforcement/agent/runner.py
lean_reinforcement/agent/__init__.py
lean_reinforcement/agent/mcts/alphazero.py
lean_reinforcement/agent/mcts/base_mcts.py
lean_reinforcement/agent/mcts/__init__.py
lean_reinforcement/agent/mcts/guidedrollout.py
lean_reinforcement/agent/mcts/mcts_cy/alphazero_cy.html
