Metadata-Version: 2.4
Name: lean_reinforcement
Version: 0.3.0
Summary: Reinforcement learning for Lean theorem proving
Requires-Python: >=3.10
License-File: LICENSE
Requires-Dist: lean-dojo
Requires-Dist: wandb
Requires-Dist: pytorch-lightning[extra]
Requires-Dist: transformers
Requires-Dist: gymnasium
Requires-Dist: loguru
Requires-Dist: networkx
Requires-Dist: lxml
Requires-Dist: deepspeed
Requires-Dist: rank_bm25
Requires-Dist: vllm
Requires-Dist: tqdm
Requires-Dist: numpy
Requires-Dist: matplotlib
Requires-Dist: jupyter
Requires-Dist: ipykernel
Requires-Dist: torch
Requires-Dist: PyGithub
Requires-Dist: openai
Requires-Dist: pre-commit
Requires-Dist: autoflake
Requires-Dist: types-tqdm
Requires-Dist: types-setuptools
Requires-Dist: cython
Dynamic: license-file
